aslookup/__init__.py
aslookup/cli.py
aslookup/exceptions.py
aslookup/lookup.py
aslookup-2.0.0.dist-info/METADATA
aslookup-2.0.0.dist-info/WHEEL
aslookup-2.0.0.dist-info/entry_points.txt
aslookup-2.0.0.dist-info/licenses/LICENSE
aslookup-2.0.0.dist-info/RECORD
