Metadata-Version: 2.4
Name: aslookup
Version: 2.0.0
Summary: IP to ASN routing data query script
Project-URL: Bug Tracker, https://github.com/dspruell/aslookup/issues
Project-URL: Homepage, https://github.com/dspruell/aslookup
Author-email: Darren Spruell <phatbuckett@gmail.com>
License-File: LICENSE
Classifier: Development Status :: 5 - Production/Stable
Classifier: License :: OSI Approved :: ISC License (ISCL)
Classifier: Programming Language :: Python :: 3
Requires-Dist: aiodns
Requires-Dist: defang
Requires-Dist: dnspython
Requires-Dist: pytricia
Provides-Extra: test
Requires-Dist: pytest; extra == 'test'
Requires-Dist: pytest-asyncio; extra == 'test'
Requires-Dist: pytest-cov; extra == 'test'
Requires-Dist: pytest-mock; extra == 'test'
